gxusthjw/__init__.py
gxusthjw/axs/__init__.py
gxusthjw/axs/saxs/__init__.py
gxusthjw/axs/waxs/__init__.py
gxusthjw/commons/__init__.py
gxusthjw/commons/arrays.py
gxusthjw/commons/benchmarks.py
gxusthjw/commons/data_2d.py
gxusthjw/commons/data_2d_region.py
gxusthjw/commons/data_analyzer.py
gxusthjw/commons/data_logger.py
gxusthjw/commons/data_table.py
gxusthjw/commons/data_xy.py
gxusthjw/commons/dataframes.py
gxusthjw/commons/dicts.py
gxusthjw/commons/file_info.py
gxusthjw/commons/file_object.py
gxusthjw/commons/file_path.py
gxusthjw/commons/file_reader.py
gxusthjw/commons/folder_operator.py
gxusthjw/commons/function_object.py
gxusthjw/commons/normalizer.py
gxusthjw/commons/path_object.py
gxusthjw/commons/paths.py
gxusthjw/commons/specimen.py
gxusthjw/commons/test_arrays.py
gxusthjw/commons/test_benchmarks.py
gxusthjw/commons/test_data_2d.py
gxusthjw/commons/test_data_2d_region.py
gxusthjw/commons/test_data_analyzer.py
gxusthjw/commons/test_data_logger.py
gxusthjw/commons/test_data_table.py
gxusthjw/commons/test_data_xy.py
gxusthjw/commons/test_dataframes.py
gxusthjw/commons/test_dataframes2.py
gxusthjw/commons/test_dicts.py
gxusthjw/commons/test_file_info.py
gxusthjw/commons/test_file_object.py
gxusthjw/commons/test_file_path.py
gxusthjw/commons/test_file_reader.py
gxusthjw/commons/test_folder_operator.py
gxusthjw/commons/test_normalize.py
gxusthjw/commons/test_path_object.py
gxusthjw/commons/test_paths.py
gxusthjw/commons/test_specimen.py
gxusthjw/commons/test_tests.py
gxusthjw/commons/test_typings.py
gxusthjw/commons/test_unique_object.py
gxusthjw/commons/tests.py
gxusthjw/commons/typings.py
gxusthjw/commons/unique_object.py
gxusthjw/filters/__init__.py
gxusthjw/filters/data_2d_region_savgol_filters.py
gxusthjw/filters/data_2d_region_view_savgol_filters.py
gxusthjw/filters/savgol_filters.py
gxusthjw/filters/test_data_2d_region_savgol_filters.py
gxusthjw/filters/test_savgol_filters.py
gxusthjw/findpeaks/__init__.py
gxusthjw/findpeaks/ampd_algorithm.py
gxusthjw-202506300929.dist-info/LICENSE
gxusthjw-202506300929.dist-info/METADATA
gxusthjw-202506300929.dist-info/WHEEL
gxusthjw-202506300929.dist-info/top_level.txt
gxusthjw-202506300929.dist-info/RECORD
