Metadata-Version: 2.1
Name: gxusthjw
Version: 202506300929
Summary: the python packages of gxusthjw.
Home-page: https://codeup.aliyun.com/67ee2f12c4c3142d59ce9a51/Pythons/gxusthjw-packages
Author: gxusthjw
Author-email: jiweihuang@vip.163.com
License: MIT
Classifier: Topic :: Software Development :: Libraries :: Python Modules
Classifier: Programming Language :: Python
Classifier: Programming Language :: Python :: 3
Classifier: Programming Language :: Python :: 3.7
Classifier: Programming Language :: Python :: 3.8
Classifier: Programming Language :: Python :: 3.9
Classifier: Programming Language :: Python :: 3.10
Classifier: Programming Language :: Python :: 3.11
Classifier: Programming Language :: Python :: 3.12
Classifier: Programming Language :: Python :: Implementation :: CPython
License-File: LICENSE
Requires-Dist: setuptools
Requires-Dist: pytest
Requires-Dist: cython
Requires-Dist: chardet
Requires-Dist: openpyxl
Requires-Dist: numpy
Requires-Dist: scipy
Requires-Dist: sympy
Requires-Dist: pandas
Requires-Dist: matplotlib
Requires-Dist: statsmodels
Requires-Dist: lmfit
Requires-Dist: pybaselines
Requires-Dist: ampdLib
Requires-Dist: pyopencl
Requires-Dist: pyopengl
Requires-Dist: pyopengl-accelerate
Requires-Dist: nmrglue
Requires-Dist: pyFAI
